.checkignore
.codacy.yml
.gitattributes
.gitignore
.travis.yml
LICENSE
MANIFEST.in
README.md
RELEASE_NOTES.rst
VERSION
bquery.png
pyproject.toml
requirements.txt
setup.cfg
setup.py
.circleci/config.yml
bquery/__init__.py
bquery/carray.py
bquery/ctable.py
bquery/ctable_ext.c
bquery/ctable_ext.pyx
bquery/khash.h
bquery/khash.pxd
bquery/khash_python.h
bquery/toplevel.py
bquery.egg-info/PKG-INFO
bquery.egg-info/SOURCES.txt
bquery.egg-info/dependency_links.txt
bquery.egg-info/requires.txt
bquery.egg-info/top_level.txt
bquery.egg-info/zip-safe
bquery/benchmarks/bench_groupby.ipynb
bquery/benchmarks/bench_groupby.py
bquery/benchmarks/bench_pos.py
bquery/benchmarks/taxi/Taxi Set.ipynb
bquery/benchmarks/taxi/__init__.py
bquery/benchmarks/taxi/load.py
bquery/benchmarks/vb_suite/README.md
bquery/benchmarks/vb_suite/run_suite.py
bquery/benchmarks/vb_suite/suite.py
bquery/benchmarks/vb_suite/vb_groupby.py
bquery/tests/__init__.py
bquery/tests/test_ctable.py