Metadata-Version: 2.1
Name: bquery
Version: 0.2.14
Summary: A query and aggregation framework for Bcolz
Home-page: https://github.com/visualfabriq/b4query
Author: Carst Vaartjes
Author-email: cvaartjes@visualfabriq.com
Maintainer: Carst Vaartjes
Maintainer-email: cvaartjes@visualfabriq.com
License: MIT
Platform: any
Classifier: Development Status :: 4 - Beta
Classifier: Intended Audience :: Developers
Classifier: Intended Audience :: Information Technology
Classifier: Intended Audience :: Science/Research
Classifier: License :: OSI Approved :: BSD License
Classifier: Programming Language :: Python
Classifier: Topic :: Software Development :: Libraries :: Python Modules
Classifier: Operating System :: Microsoft :: Windows
Classifier: Operating System :: Unix
Classifier: Programming Language :: Python :: 2
Classifier: Programming Language :: Python :: 2.7
Classifier: Programming Language :: Python :: 3
Classifier: Programming Language :: Python :: 3.5
Classifier: Programming Language :: Python :: 3.6
Classifier: Programming Language :: Python :: 3.7
Provides-Extra: test
Provides-Extra: optional
